aternos/__init__.py
aternos/main.py
aternos/server.py
aternos_client-0.1.5.dist-info/WHEEL
aternos_client-0.1.5.dist-info/entry_points.txt
aternos_client-0.1.5.dist-info/METADATA
aternos_client-0.1.5.dist-info/RECORD
