Metadata-Version: 2.1
Name: aternos-client
Version: 0.1.5
Summary: A simple client to connect on Aternos server
Author: qrillet
Author-email: quentin.rillet@gmail.com
Requires-Python: >=3.8
Classifier: Programming Language :: Python :: 3
Classifier: Programming Language :: Python :: 3.8
Classifier: Programming Language :: Python :: 3.9
Classifier: Programming Language :: Python :: 3.10
Classifier: Programming Language :: Python :: 3.11
Requires-Dist: asyncio (>=3.4.3,<4.0.0)
Requires-Dist: python-aternos (>=2.1.3,<3.0.0)
Requires-Dist: typer[all] (>=0.7.0,<0.8.0)
